utils/__init__.py
utils/user_agent.py
daraz_scrapper-0.1.1.dist-info/METADATA
daraz_scrapper-0.1.1.dist-info/WHEEL
daraz_scrapper-0.1.1.dist-info/top_level.txt
daraz_scrapper-0.1.1.dist-info/RECORD
